cai_causal_discovery/__init__.py
cai_causal_discovery-0.0.0.dist-info/WHEEL
cai_causal_discovery-0.0.0.dist-info/METADATA
cai_causal_discovery-0.0.0.dist-info/RECORD
