Metadata-Version: 2.1
Name: cai-causal-discovery
Version: 0.0.0
Summary: Causal discovery package focusing on full graph causal discovery for observational data with support for latent variables and the incorporation of domain/background knowledge.
Author: causaLens
Author-email: opensource@causalens.com
Requires-Python: >=3.8,<4.0
Classifier: Programming Language :: Python :: 3
Classifier: Programming Language :: Python :: 3.8
Classifier: Programming Language :: Python :: 3.9
Classifier: Programming Language :: Python :: 3.10
Classifier: Programming Language :: Python :: 3.11
